elna/__init__.py
elna/classes.py
elna/core.py
elna/exceptions.py
elna/smartmeter.py
elnasmartmeter-1.1.1.dist-info/LICENSE
elnasmartmeter-1.1.1.dist-info/METADATA
elnasmartmeter-1.1.1.dist-info/WHEEL
elnasmartmeter-1.1.1.dist-info/top_level.txt
elnasmartmeter-1.1.1.dist-info/RECORD
