Metadata-Version: 2.1
Name: elnasmartmeter
Version: 1.1.1
Summary: A simple library for the E.ON Elna API written in Python 3.
Home-page: https://github.com/bitcanon/elnasmartmeter
Author: Mikael Schultz
Author-email: bitcanon@pm.me
Classifier: Programming Language :: Python :: 3
Classifier: License :: OSI Approved :: MIT License
Classifier: Operating System :: OS Independent
Requires-Python: >=3.6
License-File: LICENSE
Requires-Dist: requests
Requires-Dist: python-dateutil
